clutter_catcher/__init__.py
clutter_catcher/analyzer.py
clutter_catcher/cli.py
clutter_catcher/dependencies.py
clutter_catcher/imports_resolver.py
clutter_catcher/utils.py
cluttercatcher-0.1.1.dist-info/LICENSE
cluttercatcher-0.1.1.dist-info/METADATA
cluttercatcher-0.1.1.dist-info/WHEEL
cluttercatcher-0.1.1.dist-info/entry_points.txt
cluttercatcher-0.1.1.dist-info/RECORD
